smac/__init__.py
smac/callbacks.py
smac/extras_require.json
smac/requirements.txt
smac/smac_cli.py
smac/configspace/__init__.py
smac/configspace/util.py
smac/epm/__init__.py
smac/epm/base_epm.py
smac/epm/base_gp.py
smac/epm/base_imputor.py
smac/epm/base_rf.py
smac/epm/gaussian_process.py
smac/epm/gaussian_process_mcmc.py
smac/epm/gp_base_prior.py
smac/epm/gp_kernels.py
smac/epm/random_epm.py
smac/epm/rf_with_instances.py
smac/epm/rfr_imputator.py
smac/epm/uncorrelated_mo_rf_with_instances.py
smac/epm/util_funcs.py
smac/facade/__init__.py
smac/facade/func_facade.py
smac/facade/hyperband_facade.py
smac/facade/roar_facade.py
smac/facade/smac_ac_facade.py
smac/facade/smac_bb_facade.py
smac/facade/smac_hpo_facade.py
smac/facade/smac_mf_facade.py
smac/facade/experimental/__init__.py
smac/facade/experimental/hydra_facade.py
smac/facade/experimental/psmac_facade.py
smac/initial_design/__init__.py
smac/initial_design/default_configuration_design.py
smac/initial_design/factorial_design.py
smac/initial_design/initial_design.py
smac/initial_design/latin_hypercube_design.py
smac/initial_design/random_configuration_design.py
smac/initial_design/sobol_design.py
smac/intensification/__init__.py
smac/intensification/abstract_racer.py
smac/intensification/hyperband.py
smac/intensification/intensification.py
smac/intensification/parallel_scheduling.py
smac/intensification/simple_intensifier.py
smac/intensification/successive_halving.py
smac/optimizer/__init__.py
smac/optimizer/acquisition.py
smac/optimizer/ei_optimization.py
smac/optimizer/epm_configuration_chooser.py
smac/optimizer/pSMAC.py
smac/optimizer/random_configuration_chooser.py
smac/optimizer/smbo.py
smac/runhistory/__init__.py
smac/runhistory/runhistory.py
smac/runhistory/runhistory2epm.py
smac/scenario/__init__.py
smac/scenario/scenario.py
smac/stats/__init__.py
smac/stats/stats.py
smac/tae/__init__.py
smac/tae/base.py
smac/tae/dask_runner.py
smac/tae/execute_func.py
smac/tae/execute_ta_run_aclib.py
smac-1.1.1.dist-info/LICENSE
smac-1.1.1.dist-info/METADATA
smac-1.1.1.dist-info/WHEEL
smac-1.1.1.dist-info/entry_points.txt
smac-1.1.1.dist-info/top_level.txt
smac-1.1.1.dist-info/RECORD
