Metadata-Version: 2.1
Name: smac
Version: 1.1.1
Summary: SMAC3, a Python implementation of 'Sequential Model-based Algorithm Configuration'.
Home-page: UNKNOWN
Author: Marius Lindauer, Katharina Eggensperger, Matthias Feurer, André Biedenkapp,  \
Author-email: "fh@cs.uni-freiburg.de"
License: 3-clause BSD
Keywords: machine learning,algorithm configuration,hyperparameter optimization,tuning
Platform: Linux
Classifier: Development Status :: 3 - Alpha
Classifier: Topic :: Utilities
Classifier: Topic :: Scientific/Engineering
Classifier: Topic :: Scientific/Engineering :: Artificial Intelligence
Classifier: License :: OSI Approved :: BSD License
Requires-Python: >=3.7
License-File: LICENSE
Requires-Dist: numpy (>=1.7.1)
Requires-Dist: scipy (>=1.7.0)
Requires-Dist: psutil
Requires-Dist: pynisher (>=0.4.1)
Requires-Dist: ConfigSpace (<0.5,>=0.4.14)
Requires-Dist: joblib
Requires-Dist: scikit-learn (>=0.22.0)
Requires-Dist: pyrfr (>=0.8.0)
Requires-Dist: dask
Requires-Dist: distributed
Requires-Dist: emcee (>=3.0.0)
Provides-Extra: all
Requires-Dist: mypy ; extra == 'all'
Requires-Dist: pre-commit ; extra == 'all'
Requires-Dist: sphinx-gallery (==0.10.0) ; extra == 'all'
Requires-Dist: sphinx (==4.2.0) ; extra == 'all'
Requires-Dist: pytest-forked ; extra == 'all'
Requires-Dist: image (==1.5.33) ; extra == 'all'
Requires-Dist: flaky ; extra == 'all'
Requires-Dist: pytest (>=4.6) ; extra == 'all'
Requires-Dist: bs4 (==0.0.1) ; extra == 'all'
Requires-Dist: pytest-cov ; extra == 'all'
Requires-Dist: pytest-timeout ; extra == 'all'
Provides-Extra: documentation
Requires-Dist: sphinx (==4.2.0) ; extra == 'documentation'
Requires-Dist: sphinx-gallery (==0.10.0) ; extra == 'documentation'
Requires-Dist: bs4 (==0.0.1) ; extra == 'documentation'
Requires-Dist: image (==1.5.33) ; extra == 'documentation'
Provides-Extra: test
Requires-Dist: pytest (>=4.6) ; extra == 'test'
Requires-Dist: mypy ; extra == 'test'
Requires-Dist: pytest-timeout ; extra == 'test'
Requires-Dist: flaky ; extra == 'test'
Requires-Dist: pre-commit ; extra == 'test'
Requires-Dist: pytest-forked ; extra == 'test'
Requires-Dist: pytest-cov ; extra == 'test'
